{
    "modules":{
        "client":	                        {"table_id":"20003689","url":"client/modules/client.html"},
        "passport":	                        {"table_id":"20007359","url":"client/modules/passport.html"},
        "contacts":	                        {"table_id":"20010734","url":"client/modules/contacts.html"},
        "travel_australia":	                {"table_id":"20010739","url":"client/modules/travel_australia.html"},
        "travel_other":	                    {"table_id":"20010740","url":"client/modules/travel_other.html"},
        "residential_history":	            {"table_id":"20010741","url":"client/modules/residential_history.html"},
        "employment":	                    {"table_id":"20010742","url":"client/modules/employment.html"},
        "relatives":	                    {"table_id":"20010743","url":"client/modules/relatives.html"},
        "military":	                        {"table_id":"20010744","url":"client/modules/military.html"},
        "education":	                    {"table_id":"20007360","url":"client/modules/education.html"},
        "documents":	                    {"table_id":"20007358","url":"client/modules/documents_applicant.html"},
        "documents_job":	                {"table_id":"20007358","url":"client/modules/documents_job.html"},
        "documents_task":	                {"table_id":"20007358","url":"client/modules/documents_task.html"},
        "check_document":	                {"table_id":"20011093","url":"client/modules/check_document.html"},
        "commission":	                    {"table_id":"20010746","url":"client/modules/commission.html"},
        "insurance":	                    {"table_id":"20011185","url":"client/modules/insurance.html"},
        "service_fee":	                    {"table_id":"20011186","url":"client/modules/service_fee.html"},
        "tax_invoice":	                    {"table_id":"20011187","url":"client/modules/tax_invoice.html"},
        "main_job":	                        {"table_id":"20011188","url":"client/modules/main_job.html"},
        "admin_notes":	                    {"table_id":"20011124","url":"client/modules/admin_notes.html"},
        "rental_each_unit":	                {"table_id":"20011200","url":"client/modules/rental_each_unit.html"},
        "rental_all_units":	                {"table_id":"20011201","url":"client/modules/rental_all_units.html"},
        "institute_course":	                {"table_id":"20011202","url":"client/modules/institute_course.html"},
        "scheduler_record":	                {"table_id":"20007387","url":"client/modules/scheduler_record.html"},
        "scheduler_record_admin":	        {"table_id":"20007387","url":"client/modules/scheduler_record_admin.html"},
        "scheduler_record_de":	            {"table_id":"20007387","url":"client/modules/scheduler_record_de.html"},
        "scheduler_record_not_completed":   {"table_id":"20007387","url":"client/modules/scheduler_record_not_completed.html"},
        "scheduler_record_active":          {"table_id":"20007387","url":"client/modules/scheduler_record_active.html"},
        "task_record":	                    {"table_id":"20007386","url":"client/modules/task_record.html"},
        "task_record_form":	                {"table_id":"20007386","url":"client/modules/task_record.form.html"},
        "task_record_admin":	            {"table_id":"20011124","url":"client/modules/task_record_admin.html"},
        "task_not_completed":	            {"table_id":"20007386","url":"client/modules/task_not_completed.html"},
        "task_daily_not_completed":	        {"table_id":"20007386","url":"client/modules/task_daily_not_completed.html","form_module":"task_record_form"},
        "task_daily_assigned":	            {"table_id":"20007386","url":"client/modules/task_daily_assigned.html","form_module":"task_record_form"},
        "staff_payment_period":	            {"table_id":"20011203","url":"client/modules/staff_payment_period.html"},
        "staff_hours_period":	            {"table_id":"20011474","url":"client/modules/staff_hours_period.html"}
    }
}
